<?xml version="1.0" encoding="utf-8" standalone="yes"?>

<stream>
<item>
<title>[COLOR white] ---| [COLOR dodgerblue]LIVE[COLOR white]TV |---  [COLOR gold]Updated 03-05-2017 [COLOR white][/COLOR]</title>
<link>plugin://plugin.video.f4mTester/?url=http://www.youtube.com</link>
<thumbnail></thumbnail>
<item>
<title>HBO COMEDY HD</title>
<link>plugin://plugin.video.f4mTester/?url=http://51.254.44.161:9900/live/525/525/24889.ts&amp;streamtype=TSDOWNLOADER</link>
<thumbnail></thumbnail>
</item>
<item>
<title>HBO SIGNATURE HD</title>
<link>plugin://plugin.video.f4mTester/?url=http://51.254.44.161:9900/live/525/525/24887.ts&amp;streamtype=TSDOWNLOADER</link>
<thumbnail></thumbnail>
</item>
<item>
<title>HBO ZONE</title>
<link>plugin://plugin.video.f4mTester/?url=http://51.254.44.161:9900/live/525/525/24888.ts&amp;streamtype=TSDOWNLOADER</link>
<thumbnail></thumbnail>
</item>
<item>
<title>STARZ EAST</title>
<link>plugin://plugin.video.f4mTester/?url=http://51.254.44.161:9900/live/525/525/24920.ts&amp;streamtype=TSDOWNLOADER</link>
<thumbnail></thumbnail>
</item>
<item>
<title>STARZ EDGE</title>
<link>plugin://plugin.video.f4mTester/?url=http://51.254.44.161:9900/live/525/525/24921.ts&amp;streamtype=TSDOWNLOADER</link>
<thumbnail></thumbnail>
</item>
<item>
<title>USA NETWORK HD</title>
<link>plugin://plugin.video.f4mTester/?url=http://51.254.44.161:9900/live/525/525/24894.ts&amp;streamtype=TSDOWNLOADER</link>
<thumbnail></thumbnail>
</item>
<item>
<title>Sky Movies Action&Adventure</title>
<link>plugin://plugin.video.f4mTester/?url=http://51.254.44.161:9900/live/525/525/26927.ts&amp;streamtype=TSDOWNLOADER</link>
<thumbnail></thumbnail>
</item>
<item>
<title>Sky Movies Comedy</title>
<link>plugin://plugin.video.f4mTester/?url=http://51.254.44.161:9900/live/525/525/26928.ts&amp;streamtype=TSDOWNLOADER</link>
<thumbnail></thumbnail>
</item>
<item>
<title>Sky Movies Modern_Greats</title>
<link>plugin://plugin.video.f4mTester/?url=http://51.254.44.161:9900/live/525/525/26929.ts&amp;streamtype=TSDOWNLOADER</link>
<thumbnail></thumbnail>
</item>
<item>
<title>Sky Movies Premiere</title>
<link>plugin://plugin.video.f4mTester/?url=http://51.254.44.161:9900/live/525/525/26930.ts&amp;streamtype=TSDOWNLOADER</link>
<thumbnail></thumbnail>
</item>
<item>
<title>Sky Movies Select</title>
<link>plugin://plugin.video.f4mTester/?url=http://51.254.44.161:9900/live/525/525/26932.ts&amp;streamtype=TSDOWNLOADER</link>
<thumbnail></thumbnail>
</item>
<item>
<title>Sky Movies Showcase</title>
<link>plugin://plugin.video.f4mTester/?url=http://51.254.44.161:9900/live/525/525/26933.ts&amp;streamtype=TSDOWNLOADER</link>
<thumbnail></thumbnail>
</item>
<item>
<title>Sky-movies-Thriller</title>
<link>plugin://plugin.video.f4mTester/?url=http://51.254.44.161:9900/live/525/525/26917.ts&amp;streamtype=TSDOWNLOADER</link>
<thumbnail></thumbnail>
</item>

<item>
<title>HBO</title>
<link>http://183.88.0.69:8010/play/a00m</link>
<thumbnail></thumbnail>
</item>
<item>
<title>FX</title>
<link>http://183.88.0.69:8010/play/a023</link>
<thumbnail></thumbnail>
</item>
<item>
<title>DISNEY XD</title>
<link>http://183.88.0.69:8010/play/a00x</link>
<thumbnail></thumbnail>
</item>
<item>
<title>HBO HD</title>
<link>http://183.88.0.69:8010/play/a00u</link>
<thumbnail></thumbnail>
</item>
<item>
<title>FOX CRIME</title>
<link>http://183.88.0.69:8010/play/a020</link>
<thumbnail></thumbnail>
</item>
<item>
<title>FOX ACTION MOVIES HD</title>
<link>http://183.88.0.69:8010/play/a010</link>
<thumbnail></thumbnail>
</item>
<item>
<title>DIVA UNIVERSAL</title>
<link>http://183.88.0.69:8010/play/a03n</link>
<thumbnail></thumbnail>
</item>

<item>
<title>UNIVERSAL SD</title>
<link>http://183.88.0.69:8010/play/a03m</link>
<thumbnail></thumbnail>
</item>
<item>
<title>CNN</title>
<link>http://183.88.0.69:8010/play/a00l</link>
<thumbnail></thumbnail>
</item>
<item>
<title>CARTOON NETWORK</title>
<link>http://183.88.0.69:8010/play/a01b</link>
<thumbnail></thumbnail>
</item>
<item>
<title>COMEDY CENTRAL</title>
<link>http://183.88.0.69:8010/play/a03b</link>
<thumbnail></thumbnail>
</item>
<item>
<title>NICKJR</title>
<link>http://183.88.0.69:8010/play/a01c</link>
<thumbnail></thumbnail>
</item>
<item>
<title>BBC WORLD NEWS</title>
<link>http://183.88.0.69:8010/play/a03g</link>
<thumbnail></thumbnail>
</item>
<item>
<title>SKYNET MOVIES HD</title>
<link>http://183.88.0.69:8010/play/a00v</link>
<thumbnail></thumbnail>
</item>
<item>
<title>E!</title>
<link>http://183.88.0.69:8010/play/a03o</link>
<thumbnail></thumbnail>
</item>
<item>
<title>ASN</title>
<link>http://183.88.0.69:8010/play/a02p</link>
<thumbnail></thumbnail>
</item>
<item>
<title>WORLD MOVIES</title>
<link>http://183.88.0.69:8010/play/a01k</link>
<thumbnail></thumbnail>
</item>
<item>
<title>UP TO DATE</title>
<link>http://183.88.0.69:8010/play/a03a</link>
<thumbnail></thumbnail>
</item>
<item>
<title>MWD</title>
<link>http://183.88.0.69:8010/play/a014</link>
<thumbnail></thumbnail>
</item>
<item>
<title>BBC CBEEBIES</title>
<link>http://183.88.0.69:8010/play/a03f</link>
<thumbnail></thumbnail>
</item>
<item>
<title>SKYNET SPORTS HD</title>
<link>http://183.88.0.69:8010/play/a00r</link>
<thumbnail></thumbnail>
</item>
<item>
<title>SUN TV</title>
<link>http://183.88.0.69:8010/play/a00o</link>
<thumbnail></thumbnail>
</item>
<item>
<title>FOX MOVIES PREMIUM</title>
<link>http://183.88.0.69:8010/play/a01l</link>
<thumbnail></thumbnail>
</item>
<item>
<title>SKYNET SPORTS-1</title>
<link>http://183.88.0.69:8010/play/a02j</link>
<thumbnail></thumbnail>
</item>
<item>
<title>SKYNET SPORTS-2</title>
<link>http://183.88.0.69:8010/play/a02k</link>
<thumbnail></thumbnail>
</item>
<item>
<title>BABY TV</title>
<link>http://183.88.0.69:8010/play/a01e</link>
<thumbnail></thumbnail>
</item>
<item>
<title>NAT GEO PEOPLE</title>
<link>http://183.88.0.69:8010/play/a02z</link>
<thumbnail></thumbnail>
</item>
<item>
<title>ZEE TV</title>
<link>http://183.88.0.69:8010/play/a01z</link>
<thumbnail></thumbnail>
</item>
<item>
<title>SKYNET CARTOON</title>
<link>http://183.88.0.69:8010/play/a01d</link>
<thumbnail></thumbnail>
</item>
<item>
<title>EURO SPORTS NEWS</title>
<link>http://183.88.0.69:8010/play/a00g</link>
<thumbnail></thumbnail>
</item>
<item>
<title>NICKELODEON</title>
<link>http://183.88.0.69:8010/play/a01f</link>
<thumbnail></thumbnail>
</item>
<item>
<title>FOX SPORTS 1</title>
<link>http://183.88.0.69:8010/play/a02m</link>
<thumbnail></thumbnail>
</item>
<item>
<title>CHANNEL 9</title>
<link>http://183.88.0.69:8010/play/a01a</link>
<thumbnail></thumbnail>
</item>
<item>
<title>ASIAN MOVIES</title>
<link>http://183.88.0.69:8010/play/a01j</link>
<thumbnail></thumbnail>
</item>
<item>
<title>HOME CHANNEL</title>
<link>http://183.88.0.69:8010/play/a03t</link>
<thumbnail></thumbnail>
</item>
<item>
<title>FOX SPORTS 3</title>
<link>http://183.88.0.69:8010/play/a02o</link>
<thumbnail></thumbnail>
</item>

<item>
<title>DISCOVERY</title>
<link>http://183.88.0.69:8010/play/a031</link>
<thumbnail></thumbnail>
</item>
<item>
<title>HEALTH</title>
<link>http://183.88.0.69:8010/play/a03r</link>
<thumbnail></thumbnail>
</item>
<item>
<title>AGRICULTURE/FOREST</title>
<link>http://183.88.0.69:8010/play/a03q</link>
<thumbnail></thumbnail>
</item>
<item>
<title>CI</title>
<link>http://183.88.0.69:8010/play/a00j</link>
<thumbnail></thumbnail>
</item>
<item>
<title>GLOBALNET</title>
<link>http://183.88.0.69:8010/play/a039</link>
<thumbnail></thumbnail>
</item>
<item>
<title>OUTDOOR CHANNEL</title>
<link>http://183.88.0.69:8010/play/a03d</link>
<thumbnail></thumbnail>
</item>
<item>
<title>CINEMAX</title>
<link>http://183.88.0.69:8010/play/a00n</link>
<thumbnail></thumbnail>
</item>
<item>
<title>EDUCATION CHANNEL</title>
<link>http://183.88.0.69:8010/play/a03p</link>
<thumbnail></thumbnail>
</item>
<item>
<title>LIFETIME</title>
<link>http://183.88.0.69:8010/play/a03l</link>
<thumbnail></thumbnail>
</item>
<item>
<title>DMAX</title>
<link>http://183.88.0.69:8010/play/a035</link>
<thumbnail></thumbnail>
</item>
<item>
<title>H2</title>
<link>http://183.88.0.69:8010/play/a03k</link>
<thumbnail></thumbnail>
</item>
<item>
<title>MOTORVISION</title>
<link>http://183.88.0.69:8010/play/a03j</link>
<thumbnail></thumbnail>
</item>
<item>
<title>FOX FAMILY MOVIES</title>
<link>http://183.88.0.69:8010/play/a01m</link>
<thumbnail></thumbnail>
</item>
<item>
<title>M-BIZ</title>
<link>http://183.88.0.69:8010/play/a018</link>
<thumbnail></thumbnail>
</item>
<item>
<title>EDGE SPORTS</title>
<link>http://183.88.0.69:8010/play/a03i</link>
<thumbnail></thumbnail>
</item>




<item>
<title>ABC NEWS</title>
<link>http://abclive.abcnews.com/i/abc_live4@136330/index_1200_av-b.m3u8</link>
<thumbnail></thumbnail>
</item>
<item>
<title>FOX NEWS</title>
<link>http://iphone-streaming.ustream.tv:80/uhls/4381960/streams/live/playlist.m3u8</link>
<thumbnail></thumbnail>
</item>
<item>
<title>CBS NEWS HD</title>
<link>http://cbsnewshd-lh.akamaihd.net/i/CBSNHD_7@199302/index_700_av-p.m3u8</link>
<thumbnail></thumbnail>
</item>
<item>
<title>BLOOMBERG HD</title>
<link>http://btv-i.akamaihd.net/hls/live/202760/btvusa_ios/P1/M24K.m3u8</link>
<thumbnail></thumbnail>
</item>
<item>
<title>H2</title>
<link>http://fluvod1.giniko.com/all-documentaries/all-documentaries/tracks-5,6/index.m3u8</link>
<thumbnail></thumbnail>
</item>
<item>
<title>DISCOVERY CHANNEL HD</title>
<link>http://208.86.19.13:8080/live/31.stream/index.m3u8</link>
<thumbnail></thumbnail>
</item>
<item>
<title>ANIMAL PLANET HD</title>
<link>http://iphone-streaming.ustream.tv/uhls/12762028/streams/live/iphone/playlist.m3u8</link>
<thumbnail></thumbnail>
</item>
<item>
<title>NASA TV HD</title>
<link>http://nasatv-lh.akamaihd.net/i/NASA_101@319270/master.m3u8</link>
<thumbnail></thumbnail>
</item>
<item>
<title>NHK WORLD HD</title>
<link>https://nhkwtvglobal-i.akamaihd.net/hls/live/263941/nhkwtvglobal/index_1180.m3u8</link>
<thumbnail></thumbnail>
</item>
<item>
<title>Arirang</title>
<link>http://amdlive.ctnd.com.edgesuite.net/arirang_1ch/smil:arirang_1ch.smil/playlist.m3u8</link>
<thumbnail></thumbnail>
</item>
<item>
<title>MBC</title>
<link>http://119.202.61.202:1935/live/livetv/playlist.m3u8</link>
<thumbnail></thumbnail>
</item>
<item>
<title>RT DOCUMENTARY CHANNEL</title>
<link>http://rt.ashttp.visionip.tv:1935/live/RT_Doc-SD/livestream.m3u8</link>
<thumbnail></thumbnail>
</item>
<item>
<title>RAI NEWS</title>
<link>http://b2everyrai-lh.akamaihd.net/i/rainews_1@179616/index_1200_av-p.m3u8</link>
<thumbnail></thumbnail>
</item>
<item>
<title>HISTORY LAB – ITÁLIA</title>
<link>http://wma10.fluidstream.net/HistoryLab/livestream/playlist.m3u8</link>
<thumbnail></thumbnail>
</item>
<item>
<title>DW HD</title>
<link>http://dwstream5-lh.akamaihd.net/i/dwstream5_live@124540/master.m3u8</link>
<thumbnail></thumbnail>
</item>
<item>
<title>FRANCE 24</title>
<link>http://f24hls-i.akamaihd.net/hls/live/221193/F24_EN_LO_HLS/master_900.m3u8</link>
<thumbnail></thumbnail>
</item>
<item>
<title>TV5 MONDE</title>
<link>http://hlslive.lcdn.une.net.co:80/v1/AUTH_HLSLIVE/TV5/tu1_manifest.m3u8</link>
<thumbnail></thumbnail>
</item>

<item>
<title>Nicktoons</title>
<link>http://208.86.19.13:8080/live/15.stream/index.m3u8</link>
<thumbnail></thumbnail>
</item>
<item>
<title>TNT</title>
<link>http://208.86.19.13:8080/live/16.stream/index.m3u8</link>
<thumbnail></thumbnail>
</item>
<item>
<title>CNN</title>
<link>http://208.86.19.13:8080/live/20.stream/index.m3u8</link>
<thumbnail></thumbnail>
</item>
<item>
<title>Freeform</title>
<link>http://208.86.19.13:8080/live/27.stream/index.m3u8</link>
<thumbnail></thumbnail>
</item>
<item>
<title>Discovery</title>
<link>http://208.86.19.13:8080/live/31.stream/index.m3u8</link>
<thumbnail></thumbnail>
</item>
<item>
<title>BBC America</title>
<link>http://208.86.19.13:8080/live/34.stream/index.m3u8</link>
<thumbnail></thumbnail>
</item>
<item>
<title>CBS 2</title>
<link>http://208.86.19.13:8080/live/101.stream/index.m3u8</link>
<thumbnail></thumbnail>
</item>
<item>
<title>NBC 4</title>
<link>http://208.86.19.123:8080/live/102.stream/index.m3u8</link>
<thumbnail></thumbnail>
</item>
<item>
<title>Fox 5</title>
<link>http://208.86.19.13:8080/live/103.stream/index.m3u8</link>
<thumbnail></thumbnail>
</item>
<item>
<title>ABC 7</title>
<link>http://208.86.19.123:8080/live/104.stream/index.m3u8</link>
<thumbnail></thumbnail>
</item>
<item>
<title>My 9</title>
<link>http://208.86.19.13:8080/live/105.stream/index.m3u8</link>
<thumbnail></thumbnail>
</item>
<item>
<title>PIX 11</title>
<link>http://208.86.19.13:8080/live/106.stream/index.m3u8</link>
<thumbnail></thumbnail>
</item>
<item>
<title>PBS THIRTEEN</title>
<link>http://208.86.19.123:8080/live/107.stream/index.m3u8</link>
<thumbnail></thumbnail>
</item>
<item>
<title>WLIW 21</title>
<link>http://208.86.19.13:8080/live/108.stream/index.m3u8</link>
<thumbnail></thumbnail>
</item>
<item>
<title>ION</title>
<link>http://208.86.19.123:8080/live/109.stream/index.m3u8</link>
<thumbnail></thumbnail>
</item>
<item>
<title>CNN</title>
<link>http://208.86.19.13:8080/live/20.stream/index.m3u8</link>
<thumbnail></thumbnail>
</item>
<item>
<title>ME TV</title>
<link>http://208.86.19.13:8080/live/32.stream/index.m3u8</link>
<thumbnail></thumbnail>
</item>
<item>
<title>FILM ASIA</title>
<link>http://208.86.19.13:8080/live/835.stream/index.m3u8</link>
<thumbnail></thumbnail>
</item>
<item>
<title>PLUS TV</title>
<link>http://208.86.19.13:8080/live/837.stream/index.m3u8</link>
<thumbnail></thumbnail>
</item>
<item>
<title>BTV WORLD</title>
<link>http://208.86.19.13:8080/live/836.stream/index.m3u8</link>
<thumbnail></thumbnail>
</item>
<item>
<title>CINEMA-1 TV</title>
<link>http://208.86.19.13:8080/live/840.stream/index.m3u8</link>
<thumbnail></thumbnail>
</item>
<item>
<title>OZTV</title>
<link>http://208.86.19.13:8080/live/103.stream/index.m3u8</link>
<thumbnail></thumbnail>
</item>
<item>
<title>PIX2</title>
<link>http://208.86.19.13:8080/live/106.stream/index.m3u8</link>
<thumbnail></thumbnail>
</item>
<item>
<title>EI</title>
<link>http://208.86.19.13:8080/live/108.stream/index.m3u8</link>
<thumbnail></thumbnail>
</item>
<item>
<title>DISH TV</title>
<link>http://208.86.19.13:8080/live/628.stream/index.m3u8</link>
<thumbnail></thumbnail>
</item>
<item>
<title>DUNYA TV</title>
<link>http://208.86.19.13:8080/live/629.stream/index.m3u8</link>
<thumbnail></thumbnail>
</item>
<item>
<title>DWV</title>
<link>http://208.86.19.13:8080/live/630.stream/index.m3u8</link>
<thumbnail></thumbnail>
</item>
<item>
<title>EXNEWS</title>
<link>http://208.86.19.13:8080/live/631.stream/index.m3u8</link>
<thumbnail></thumbnail>
</item>
<item>
<title>NATIONAL</title>
<link>http://208.86.19.13:8080/live/632.stream/index.m3u8</link>
<thumbnail></thumbnail>
</item>
<item>
<title>9 KANAL</title>
<link>http://208.86.19.13:8080/live/803.stream/index.m3u8</link>
<thumbnail></thumbnail>
</item>
<item>
<title>ETV</title>
<link>http://208.86.19.13:8080/live/804.stream/index.m3u8</link>
<thumbnail></thumbnail>
</item>
<item>
<title>JAMUNA TV</title>
<link>http://208.86.19.13:8080/live/805.stream/index.m3u8</link>
<thumbnail></thumbnail>
</item>
<item>
<title>ATN</title>
<link>http://208.86.19.13:8080/live/806.stream/index.m3u8</link>
<thumbnail></thumbnail>
</item>
<item>
<title>A PLUS</title>
<link>http://208.86.19.13:8080/live/831.stream/index.m3u8</link>
<thumbnail></thumbnail>
</item>
<item>
<title>TV</title>
<link>http://208.86.19.13:8080/live/832.stream/index.m3u8</link>
<thumbnail></thumbnail>
</item>
<item>
<title>STAR LITE</title>
<link>http://208.86.19.13:8080/live/834.stream/index.m3u8</link>
<thumbnail></thumbnail>
</item>






</stream>
