<?xml version="1.0" encoding="utf-8" standalone="yes"?>

<stream>
<item>
<title>[COLOR white]--| [COLOR dodgerblue]LIVE[COLOR white]TV |--  [COLOR gold]Updated 02-18-2017 [COLOR white][/COLOR]</title>
<link>plugin://plugin.video.f4mTester/?url=http://www.youtube.com</link>
<thumbnail></thumbnail>
</item>
<item>
<title>Sky Cinema Crime & Thriller</title>
<link>plugin://plugin.video.f4mTester/?url=http://s1.finoip.com:20000/live/mark/mark/3649.ts&amp;streamtype=TSDOWNLOADER</link>
<thumbnail></thumbnail>
</item>
<item>
<title>Sky Cinema Action & Adventure</title>
<link>plugin://plugin.video.f4mTester/?url=http://s1.finoip.com:20000/live/mark/mark/3638.ts&amp;streamtype=TSDOWNLOADER</link>
<thumbnail></thumbnail>
</item>
<item>
<title>Sky Cinema Christmass</title>
<link>plugin://plugin.video.f4mTester/?url=http://s1.finoip.com:20000/live/mark/mark/3642.ts&amp;streamtype=TSDOWNLOADER</link>
<thumbnail></thumbnail>
</item>
<item>
<title>Sky Cinema Comedy</title>
<link>plugin://plugin.video.f4mTester/?url=http://s1.finoip.com:20000/live/mark/mark/3640.ts&amp;streamtype=TSDOWNLOADER</link>
<thumbnail></thumbnail>
</item>
<item>
<title>Sky Cinema Disney</title>
<link>plugin://plugin.video.f4mTester/?url=http://s1.finoip.com:20000/live/mark/mark/3641.ts&amp;streamtype=TSDOWNLOADER</link>
<thumbnail></thumbnail>
</item>
<item>
<title>Sky Cinema Family</title>
<link>plugin://plugin.video.f4mTester/?url=http://s1.finoip.com:20000/live/mark/mark/3643.ts&amp;streamtype=TSDOWNLOADER</link>
<thumbnail></thumbnail>
</item>
<item>
<title>Sky Cinema Hits</title>
<link>plugin://plugin.video.f4mTester/?url=http://s1.finoip.com:20000/live/mark/mark/3648.ts&amp;streamtype=TSDOWNLOADER</link>
<thumbnail></thumbnail>
</item>
<item>
<title>Sky Cinema Modern Greats</title>
<link>plugin://plugin.video.f4mTester/?url=http://s1.finoip.com:20000/live/mark/mark/3644.ts&amp;streamtype=TSDOWNLOADER</link>
<thumbnail></thumbnail>
</item>
<item>
<title>Sky Cinema Premiere</title>
<link>plugin://plugin.video.f4mTester/?url=http://s1.finoip.com:20000/live/mark/mark/3645.ts&amp;streamtype=TSDOWNLOADER</link>
<thumbnail></thumbnail>
</item>
<item>
<title>Sky Cinema ScFi/Horror</title>
<link>plugin://plugin.video.f4mTester/?url=http://s1.finoip.com:20000/live/mark/mark/3646.ts&amp;streamtype=TSDOWNLOADER</link>
<thumbnail></thumbnail>
</item>
<item>
<title>Sky Cinema Select</title>
<link>plugin://plugin.video.f4mTester/?url=http://s1.finoip.com:20000/live/mark/mark/3647.ts&amp;streamtype=TSDOWNLOADER</link>
<thumbnail></thumbnail>
</item>
<item>
<title>True Movies</title>
<link>plugin://plugin.video.f4mTester/?url=http://s1.finoip.com:20000/live/mark/mark/5518.ts&amp;streamtype=TSDOWNLOADER</link>
<thumbnail></thumbnail>
</item>
<item>
<title>TRUE MOVIES 1</title>
<link>plugin://plugin.video.f4mTester/?url=http://s1.finoip.com:20000/live/mark/mark/3674.ts&amp;streamtype=TSDOWNLOADER</link>
<thumbnail></thumbnail>
</item>
<item>
<title>Disney Channel</title>
<link>plugin://plugin.video.f4mTester/?url=http://skyiptv.zapto.org:8000/live/iptv1790/179065287/97.ts</link>
<thumbnail></thumbnail>
</item>
<item>
<title>Discovery Science</title>
<link>plugin://plugin.video.f4mTester/?url=http://skyiptv.zapto.org:8000/live/iptv1790/179065287/98.ts&amp;streamtype=TSDOWNLOADER</link>
<thumbnail></thumbnail>
</item>
<item>
<title>Discovery Investigation</title>
<link>plugin://plugin.video.f4mTester/?url=http://skyiptv.zapto.org:8000/live/iptv1790/179065287/99.ts&amp;streamtype=TSDOWNLOADER</link>
<thumbnail></thumbnail>
</item>
<item>
<title>Discovery History</title>
<link>plugin://plugin.video.f4mTester/?url=http://skyiptv.zapto.org:8000/live/iptv1790/179065287/100.ts&amp;streamtype=TSDOWNLOADER</link>
<thumbnail></thumbnail>
</item>
<item>
<title>Channel 4</title>
<link>plugin://plugin.video.f4mTester/?url=http://skyiptv.zapto.org:8000/live/iptv1790/179065287/102.ts&amp;streamtype=TSDOWNLOADER</link>
<thumbnail></thumbnail>
</item>
<item>
<title>BT Sports 2</title>
<link>plugin://plugin.video.f4mTester/?url=http://skyiptv.zapto.org:8000/live/iptv1790/179065287/103.ts&amp;streamtype=TSDOWNLOADER</link>
<thumbnail></thumbnail>
</item>
<item>
<title>BT Sports 1</title>
<link>plugin://plugin.video.f4mTester/?url=http://skyiptv.zapto.org:8000/live/iptv1790/179065287/104.ts&amp;streamtype=TSDOWNLOADER</link>
<thumbnail></thumbnail>
</item>
<item>
<title>Boxnation</title>
<link>plugin://plugin.video.f4mTester/?url=http://skyiptv.zapto.org:8000/live/iptv1790/179065287/105.ts&amp;streamtype=TSDOWNLOADER</link>
<thumbnail></thumbnail>
</item>
<item>
<title>BBC 1</title>
<link>plugin://plugin.video.f4mTester/?url=http://skyiptv.zapto.org:8000/live/iptv1790/179065287/109.ts&amp;streamtype=TSDOWNLOADER</link>
<thumbnail></thumbnail>
</item>
<item>
<title>BBC 2</title>
<link>plugin://plugin.video.f4mTester/?url=http://skyiptv.zapto.org:8000/live/iptv1790/179065287/108.ts&amp;streamtype=TSDOWNLOADER</link>
<thumbnail></thumbnail>
</item>
<item>
<title>BBC 3</title>
<link>plugin://plugin.video.f4mTester/?url=http://skyiptv.zapto.org:8000/live/iptv1790/179065287/107.ts&amp;streamtype=TSDOWNLOADER</link>
<thumbnail></thumbnail>
</item>
<item>
<title>UK: MTV Classic</title>
<link>plugin://plugin.video.f4mTester/?url=http://skyiptv.zapto.org:8000/live/iptv1790/179065287/757.ts&amp;streamtype=TSDOWNLOADER</link>
<thumbnail></thumbnail>
</item>

<item>
<title>: Setanta sport</title>
<link>plugin://plugin.video.f4mTester/?url=http://skyiptv.zapto.org:8000/live/iptv1790/179065287/782.ts&amp;streamtype=TSDOWNLOADER</link>
<thumbnail></thumbnail>
</item>
<item>
<title>: RacingUK</title>
<link>plugin://plugin.video.f4mTester/?url=http://skyiptv.zapto.org:8000/live/iptv1790/179065287/780.ts&amp;streamtype=TSDOWNLOADER</link>
<thumbnail></thumbnail>
</item>
<item>
<title>: NickJunior</title>
<link>plugin://plugin.video.f4mTester/?url=http://skyiptv.zapto.org:8000/live/iptv1790/179065287/779.ts&amp;streamtype=TSDOWNLOADER</link>
<thumbnail></thumbnail>
</item>
<item>
<title>: MUTV</title>
<link>plugin://plugin.video.f4mTester/?url=http://skyiptv.zapto.org:8000/live/iptv1790/179065287/778.ts&amp;streamtype=TSDOWNLOADER</link>
<thumbnail></thumbnail>
</item>
<item>
<title>: liverpooltv</title>
<link>plugin://plugin.video.f4mTester/?url=http://skyiptv.zapto.org:8000/live/iptv1790/179065287/776.ts&amp;streamtype=TSDOWNLOADER</link>
<thumbnail></thumbnail>
</item>
<item>
<title>: fox uk</title>
<link>plugin://plugin.video.f4mTester/?url=http://skyiptv.zapto.org:8000/live/iptv1790/179065287/773.ts&amp;streamtype=TSDOWNLOADER</link>
<thumbnail></thumbnail>
</item>
<item>
<title>: Disney XD</title>
<link>plugin://plugin.video.f4mTester/?url=http://skyiptv.zapto.org:8000/live/iptv1790/179065287/771.ts&amp;streamtype=TSDOWNLOADER</link>
<thumbnail></thumbnail>
</item>
<item>
<title>: DiscoveryChannel</title>
<link>plugin://plugin.video.f4mTester/?url=http://skyiptv.zapto.org:8000/live/iptv1790/179065287/769.ts&amp;streamtype=TSDOWNLOADER</link>
<thumbnail></thumbnail>
</item>
<item>
<title>: ChelseaTV</title>
<link>plugin://plugin.video.f4mTester/?url=http://skyiptv.zapto.org:8000/live/iptv1790/179065287/767.ts&amp;streamtype=TSDOWNLOADER</link>
<thumbnail></thumbnail>
</item>
<item>
<title>: channel 5</title>
<link>plugin://plugin.video.f4mTester/?url=http://skyiptv.zapto.org:8000/live/iptv1790/179065287/766.ts&amp;streamtype=TSDOWNLOADER</link>
<thumbnail></thumbnail>
</item>
<item>
<title>: CartoonNetuk</title>
<link>plugin://plugin.video.f4mTester/?url=http://skyiptv.zapto.org:8000/live/iptv1790/179065287/765.ts&amp;streamtype=TSDOWNLOADER</link>
<thumbnail></thumbnail>
</item>

</stream>



